zeus_server_load/ViGEmBus_Setup_1.22.0.exe
zeus_server_load/__init__.py
zeus_server_load/__main__.py
zeus_server_load/chrome_manager.py
zeus_server_load/config_manager.py
zeus_server_load/gamepad_controller.py
zeus_server_load/hwid_manager.py
zeus_server_load/server.py
zeus_server_load/utils.py
zeus_server_load-0.0.3.dist-info/METADATA
zeus_server_load-0.0.3.dist-info/WHEEL
zeus_server_load-0.0.3.dist-info/entry_points.txt
zeus_server_load-0.0.3.dist-info/top_level.txt
zeus_server_load-0.0.3.dist-info/RECORD
