Metadata-Version: 2.1
Name: zeus-server-load
Version: 0.0.3
Summary: A server for controlling gamepad inputs and managing HWIDs.
Home-page: https://github.com/satyajiit/zeus-server-load
Author: SatyaJit Pradhan
Author-email: hello.theappstack@gmail.com
License: MIT
Classifier: Programming Language :: Python :: 3
Classifier: License :: OSI Approved :: MIT License
Classifier: Operating System :: Microsoft :: Windows
Classifier: Operating System :: POSIX :: Linux
Requires-Python: >=3.6
Requires-Dist: vgamepad
Requires-Dist: colorama
Requires-Dist: requests
